[
  {
    "date": "2025-09-11",
    "code": "9904",
    "name": "寶成",
    "market": "TWSE",
    "foreign_ratio": 0.0,
    "trust_ratio": 0.0,
    "dealer_ratio": 0.0,
    "three_inst_ratio": 0.0,
    "three_inst_ratio_change_20": 0.0
  },
  {
    "date": "2025-09-12",
    "code": "9904",
    "name": "寶成",
    "market": "TWSE",
    "foreign_ratio": 0.0,
    "trust_ratio": 0.0,
    "dealer_ratio": 0.0,
    "three_inst_ratio": 0.0,
    "three_inst_ratio_change_20": 0.0
  },
  {
    "date": "2025-09-15",
    "code": "9904",
    "name": "寶成",
    "market": "TWSE",
    "foreign_ratio": 0.0,
    "trust_ratio": 0.0,
    "dealer_ratio": 0.0,
    "three_inst_ratio": 0.0,
    "three_inst_ratio_change_20": 0.0
  },
  {
    "date": "2025-09-16",
    "code": "9904",
    "name": "寶成",
    "market": "TWSE",
    "foreign_ratio": 0.0,
    "trust_ratio": 0.0,
    "dealer_ratio": 0.0,
    "three_inst_ratio": 0.0,
    "three_inst_ratio_change_20": 0.0
  },
  {
    "date": "2025-09-17",
    "code": "9904",
    "name": "寶成",
    "market": "TWSE",
    "foreign_ratio": 0.0,
    "trust_ratio": 0.0,
    "dealer_ratio": 0.0,
    "three_inst_ratio": 0.0,
    "three_inst_ratio_change_20": 0.0
  },
  {
    "date": "2025-09-18",
    "code": "9904",
    "name": "寶成",
    "market": "TWSE",
    "foreign_ratio": 0.0,
    "trust_ratio": 0.0,
    "dealer_ratio": 0.0,
    "three_inst_ratio": 0.0,
    "three_inst_ratio_change_20": 0.0
  },
  {
    "date": "2025-09-19",
    "code": "9904",
    "name": "寶成",
    "market": "TWSE",
    "foreign_ratio": 0.0,
    "trust_ratio": 0.0,
    "dealer_ratio": 0.0,
    "three_inst_ratio": 0.0,
    "three_inst_ratio_change_20": 0.0
  },
  {
    "date": "2025-09-22",
    "code": "9904",
    "name": "寶成",
    "market": "TWSE",
    "foreign_ratio": 0.0,
    "trust_ratio": 0.0,
    "dealer_ratio": 0.0,
    "three_inst_ratio": 0.0,
    "three_inst_ratio_change_20": 0.0
  },
  {
    "date": "2025-09-23",
    "code": "9904",
    "name": "寶成",
    "market": "TWSE",
    "foreign_ratio": 0.0,
    "trust_ratio": 0.0,
    "dealer_ratio": 0.0,
    "three_inst_ratio": 0.0,
    "three_inst_ratio_change_20": 0.0
  },
  {
    "date": "2025-09-24",
    "code": "9904",
    "name": "寶成",
    "market": "TWSE",
    "foreign_ratio": 0.0,
    "trust_ratio": 0.0,
    "dealer_ratio": 0.0,
    "three_inst_ratio": 0.0,
    "three_inst_ratio_change_20": 0.0
  },
  {
    "date": "2025-09-25",
    "code": "9904",
    "name": "寶成",
    "market": "TWSE",
    "foreign_ratio": 0.0,
    "trust_ratio": 0.0,
    "dealer_ratio": 0.0,
    "three_inst_ratio": 0.0,
    "three_inst_ratio_change_20": 0.0
  },
  {
    "date": "2025-09-26",
    "code": "9904",
    "name": "寶成",
    "market": "TWSE",
    "foreign_ratio": 0.0,
    "trust_ratio": 0.0,
    "dealer_ratio": 0.0,
    "three_inst_ratio": 0.0,
    "three_inst_ratio_change_20": 0.0
  },
  {
    "date": "2025-09-30",
    "code": "9904",
    "name": "寶成",
    "market": "TWSE",
    "foreign_ratio": 0.0,
    "trust_ratio": 0.0,
    "dealer_ratio": 0.0,
    "three_inst_ratio": 0.0,
    "three_inst_ratio_change_20": 0.0
  },
  {
    "date": "2025-10-01",
    "code": "9904",
    "name": "寶成",
    "market": "TWSE",
    "foreign_ratio": 0.0,
    "trust_ratio": 0.0,
    "dealer_ratio": 0.0,
    "three_inst_ratio": 0.0,
    "three_inst_ratio_change_20": 0.0
  },
  {
    "date": "2025-10-02",
    "code": "9904",
    "name": "寶成",
    "market": "TWSE",
    "foreign_ratio": 0.0,
    "trust_ratio": 0.0,
    "dealer_ratio": 0.0,
    "three_inst_ratio": 0.0,
    "three_inst_ratio_change_20": 0.0
  },
  {
    "date": "2025-10-03",
    "code": "9904",
    "name": "寶成",
    "market": "TWSE",
    "foreign_ratio": 0.0,
    "trust_ratio": 0.0,
    "dealer_ratio": 0.0,
    "three_inst_ratio": 0.0,
    "three_inst_ratio_change_20": 0.0
  },
  {
    "date": "2025-10-07",
    "code": "9904",
    "name": "寶成",
    "market": "TWSE",
    "foreign_ratio": 41.76,
    "trust_ratio": 0.2832323271656602,
    "dealer_ratio": 0.0,
    "three_inst_ratio": 42.04323232716566,
    "three_inst_ratio_change_20": 0.0
  },
  {
    "date": "2025-10-08",
    "code": "9904",
    "name": "寶成",
    "market": "TWSE",
    "foreign_ratio": 41.79,
    "trust_ratio": 0.28604277780270115,
    "dealer_ratio": 0.0,
    "three_inst_ratio": 42.0760427778027,
    "three_inst_ratio_change_20": 0.0
  },
  {
    "date": "2025-10-09",
    "code": "9904",
    "name": "寶成",
    "market": "TWSE",
    "foreign_ratio": 42.06,
    "trust_ratio": 0.2867214830689575,
    "dealer_ratio": 0.0,
    "three_inst_ratio": 42.34672148306896,
    "three_inst_ratio_change_20": 0.0
  },
  {
    "date": "2025-10-13",
    "code": "9904",
    "name": "寶成",
    "market": "TWSE",
    "foreign_ratio": 41.72,
    "trust_ratio": 0.2878363243393102,
    "dealer_ratio": 0.0,
    "three_inst_ratio": 42.00783632433931,
    "three_inst_ratio_change_20": 0.0
  },
  {
    "date": "2025-10-14",
    "code": "9904",
    "name": "寶成",
    "market": "TWSE",
    "foreign_ratio": 41.6,
    "trust_ratio": 0.2896487388823212,
    "dealer_ratio": 0.0,
    "three_inst_ratio": 41.88964873888232,
    "three_inst_ratio_change_20": 41.88964873888232
  },
  {
    "date": "2025-10-15",
    "code": "9904",
    "name": "寶成",
    "market": "TWSE",
    "foreign_ratio": 41.74,
    "trust_ratio": 0.29080253783495696,
    "dealer_ratio": 0.0,
    "three_inst_ratio": 42.03080253783496,
    "three_inst_ratio_change_20": 42.03080253783496
  },
  {
    "date": "2025-10-16",
    "code": "9904",
    "name": "寶成",
    "market": "TWSE",
    "foreign_ratio": 41.81,
    "trust_ratio": 0.3031549736808227,
    "dealer_ratio": 0.0,
    "three_inst_ratio": 42.11315497368083,
    "three_inst_ratio_change_20": 42.11315497368083
  },
  {
    "date": "2025-10-17",
    "code": "9904",
    "name": "寶成",
    "market": "TWSE",
    "foreign_ratio": 41.9,
    "trust_ratio": 0.3053268305328431,
    "dealer_ratio": 0.0,
    "three_inst_ratio": 42.20532683053284,
    "three_inst_ratio_change_20": 42.20532683053284
  },
  {
    "date": "2025-10-20",
    "code": "9904",
    "name": "寶成",
    "market": "TWSE",
    "foreign_ratio": 42.03,
    "trust_ratio": 0.3520896233779062,
    "dealer_ratio": 0.0,
    "three_inst_ratio": 42.38208962337791,
    "three_inst_ratio_change_20": 42.38208962337791
  },
  {
    "date": "2025-10-21",
    "code": "9904",
    "name": "寶成",
    "market": "TWSE",
    "foreign_ratio": 42.04,
    "trust_ratio": 0.35948751078010055,
    "dealer_ratio": 0.0,
    "three_inst_ratio": 42.3994875107801,
    "three_inst_ratio_change_20": 42.3994875107801
  },
  {
    "date": "2025-10-22",
    "code": "9904",
    "name": "寶成",
    "market": "TWSE",
    "foreign_ratio": 42.28,
    "trust_ratio": 0.3711767497750439,
    "dealer_ratio": 0.0,
    "three_inst_ratio": 42.65117674977505,
    "three_inst_ratio_change_20": 42.65117674977505
  },
  {
    "date": "2025-10-23",
    "code": "9904",
    "name": "寶成",
    "market": "TWSE",
    "foreign_ratio": 42.22,
    "trust_ratio": 0.40341524992222094,
    "dealer_ratio": 0.0,
    "three_inst_ratio": 42.62341524992222,
    "three_inst_ratio_change_20": 42.62341524992222
  },
  {
    "date": "2025-10-27",
    "code": "9904",
    "name": "寶成",
    "market": "TWSE",
    "foreign_ratio": 42.07,
    "trust_ratio": 0.4039973414938257,
    "dealer_ratio": 0.0,
    "three_inst_ratio": 42.47399734149383,
    "three_inst_ratio_change_20": 42.47399734149383
  },
  {
    "date": "2025-10-28",
    "code": "9904",
    "name": "寶成",
    "market": "TWSE",
    "foreign_ratio": 41.9,
    "trust_ratio": 0.40433669412695394,
    "dealer_ratio": 0.0,
    "three_inst_ratio": 42.30433669412695,
    "three_inst_ratio_change_20": 42.30433669412695
  },
  {
    "date": "2025-10-29",
    "code": "9904",
    "name": "寶成",
    "market": "TWSE",
    "foreign_ratio": 41.88,
    "trust_ratio": 0.40460817623345646,
    "dealer_ratio": 0.0,
    "three_inst_ratio": 42.28460817623346,
    "three_inst_ratio_change_20": 42.28460817623346
  },
  {
    "date": "2025-10-30",
    "code": "9904",
    "name": "寶成",
    "market": "TWSE",
    "foreign_ratio": 41.75,
    "trust_ratio": 0.42206932842422373,
    "dealer_ratio": 0.0,
    "three_inst_ratio": 42.17206932842422,
    "three_inst_ratio_change_20": 42.17206932842422
  },
  {
    "date": "2025-10-31",
    "code": "9904",
    "name": "寶成",
    "market": "TWSE",
    "foreign_ratio": 41.84,
    "trust_ratio": 0.45702264963642625,
    "dealer_ratio": 0.0,
    "three_inst_ratio": 42.29702264963643,
    "three_inst_ratio_change_20": 42.29702264963643
  },
  {
    "date": "2025-11-03",
    "code": "9904",
    "name": "寶成",
    "market": "TWSE",
    "foreign_ratio": 41.52,
    "trust_ratio": 0.4586176070121287,
    "dealer_ratio": 0.0,
    "three_inst_ratio": 41.97861760701213,
    "three_inst_ratio_change_20": 41.97861760701213
  },
  {
    "date": "2025-11-04",
    "code": "9904",
    "name": "寶成",
    "market": "TWSE",
    "foreign_ratio": 41.45,
    "trust_ratio": 0.46379419388365595,
    "dealer_ratio": 0.0,
    "three_inst_ratio": 41.91379419388366,
    "three_inst_ratio_change_20": 41.91379419388366
  },
  {
    "date": "2025-11-05",
    "code": "9904",
    "name": "寶成",
    "market": "TWSE",
    "foreign_ratio": 41.5,
    "trust_ratio": 0.47523546790957244,
    "dealer_ratio": 0.0,
    "three_inst_ratio": 41.97523546790957,
    "three_inst_ratio_change_20": 41.97523546790957
  },
  {
    "date": "2025-11-06",
    "code": "9904",
    "name": "寶成",
    "market": "TWSE",
    "foreign_ratio": 41.61,
    "trust_ratio": 0.5034841991490615,
    "dealer_ratio": 0.0,
    "three_inst_ratio": 42.11348419914906,
    "three_inst_ratio_change_20": 0.07025187198340177
  },
  {
    "date": "2025-11-07",
    "code": "9904",
    "name": "寶成",
    "market": "TWSE",
    "foreign_ratio": 41.56,
    "trust_ratio": 0.5433742527916962,
    "dealer_ratio": 0.0,
    "three_inst_ratio": 42.103374252791696,
    "three_inst_ratio_change_20": 0.027331474988997684
  },
  {
    "date": "2025-11-10",
    "code": "9904",
    "name": "寶成",
    "market": "TWSE",
    "foreign_ratio": 41.46,
    "trust_ratio": 0.5433742527916962,
    "dealer_ratio": 0.0,
    "three_inst_ratio": 42.003374252791694,
    "three_inst_ratio_change_20": -0.3433472302772671
  },
  {
    "date": "2025-11-11",
    "code": "9904",
    "name": "寶成",
    "market": "TWSE",
    "foreign_ratio": 41.47,
    "trust_ratio": 0.5307909892847766,
    "dealer_ratio": 0.0,
    "three_inst_ratio": 42.00079098928477,
    "three_inst_ratio_change_20": -0.0070453350545349736
  },
  {
    "date": "2025-11-12",
    "code": "9904",
    "name": "寶成",
    "market": "TWSE",
    "foreign_ratio": 41.65,
    "trust_ratio": 0.5288140905204886,
    "dealer_ratio": 0.0,
    "three_inst_ratio": 42.17881409052049,
    "three_inst_ratio_change_20": 0.28916535163816803
  },
  {
    "date": "2025-11-13",
    "code": "9904",
    "name": "寶成",
    "market": "TWSE",
    "foreign_ratio": 41.77,
    "trust_ratio": 0.5275429773625803,
    "dealer_ratio": 0.0,
    "three_inst_ratio": 42.29754297736258,
    "three_inst_ratio_change_20": 0.2667404395276236
  },
  {
    "date": "2025-11-14",
    "code": "9904",
    "name": "寶成",
    "market": "TWSE",
    "foreign_ratio": 42.07,
    "trust_ratio": 0.5271095561795489,
    "dealer_ratio": 0.0,
    "three_inst_ratio": 42.59710955617955,
    "three_inst_ratio_change_20": 0.48395458249871837
  },
  {
    "date": "2025-11-17",
    "code": "9904",
    "name": "寶成",
    "market": "TWSE",
    "foreign_ratio": 42.02,
    "trust_ratio": 0.5252954788086356,
    "dealer_ratio": 0.0,
    "three_inst_ratio": 42.54529547880864,
    "three_inst_ratio_change_20": 0.3399686482758
  },
  {
    "date": "2025-11-18",
    "code": "9904",
    "name": "寶成",
    "market": "TWSE",
    "foreign_ratio": 41.75,
    "trust_ratio": 0.5683413083277825,
    "dealer_ratio": 0.0,
    "three_inst_ratio": 42.31834130832778,
    "three_inst_ratio_change_20": -0.06374831505012679
  },
  {
    "date": "2025-11-19",
    "code": "9904",
    "name": "寶成",
    "market": "TWSE",
    "foreign_ratio": 41.75,
    "trust_ratio": 0.6145950722231533,
    "dealer_ratio": 0.0,
    "three_inst_ratio": 42.36459507222315,
    "three_inst_ratio_change_20": -0.03489243855694468
  },
  {
    "date": "2025-11-20",
    "code": "9904",
    "name": "寶成",
    "market": "TWSE",
    "foreign_ratio": 41.76,
    "trust_ratio": 0.6296685732224941,
    "dealer_ratio": 0.0,
    "three_inst_ratio": 42.389668573222494,
    "three_inst_ratio_change_20": -0.2615081765525531
  },
  {
    "date": "2025-11-21",
    "code": "9904",
    "name": "寶成",
    "market": "TWSE",
    "foreign_ratio": 41.65,
    "trust_ratio": 0.6644182828548197,
    "dealer_ratio": 0.0,
    "three_inst_ratio": 42.31441828285482,
    "three_inst_ratio_change_20": -0.3089969670674009
  },
  {
    "date": "2025-11-24",
    "code": "9904",
    "name": "寶成",
    "market": "TWSE",
    "foreign_ratio": 41.61,
    "trust_ratio": 0.6958423366824892,
    "dealer_ratio": 0.0,
    "three_inst_ratio": 42.30584233668249,
    "three_inst_ratio_change_20": -0.16815500481133938
  },
  {
    "date": "2025-11-25",
    "code": "9904",
    "name": "寶成",
    "market": "TWSE",
    "foreign_ratio": 41.55,
    "trust_ratio": 0.7398286820243508,
    "dealer_ratio": 0.0,
    "three_inst_ratio": 42.28982868202435,
    "three_inst_ratio_change_20": -0.014508012102602663
  },
  {
    "date": "2025-11-26",
    "code": "9904",
    "name": "寶成",
    "market": "TWSE",
    "foreign_ratio": 41.88,
    "trust_ratio": 0.7393573890874625,
    "dealer_ratio": 0.0,
    "three_inst_ratio": 42.61935738908746,
    "three_inst_ratio_change_20": 0.3347492128539997
  },
  {
    "date": "2025-11-27",
    "code": "9904",
    "name": "寶成",
    "market": "TWSE",
    "foreign_ratio": 41.84,
    "trust_ratio": 0.7716297566274257,
    "dealer_ratio": 0.0,
    "three_inst_ratio": 42.61162975662743,
    "three_inst_ratio_change_20": 0.4395604282032082
  },
  {
    "date": "2025-11-28",
    "code": "9904",
    "name": "寶成",
    "market": "TWSE",
    "foreign_ratio": 41.87,
    "trust_ratio": 0.7716297566274257,
    "dealer_ratio": 0.0,
    "three_inst_ratio": 42.641629756627424,
    "three_inst_ratio_change_20": 0.34460710699099195
  },
  {
    "date": "2025-12-01",
    "code": "9904",
    "name": "寶成",
    "market": "TWSE",
    "foreign_ratio": 42.0,
    "trust_ratio": 0.7629762644826571,
    "dealer_ratio": 0.0,
    "three_inst_ratio": 42.76297626448266,
    "three_inst_ratio_change_20": 0.784358657470527
  },
  {
    "date": "2025-12-02",
    "code": "9904",
    "name": "寶成",
    "market": "TWSE",
    "foreign_ratio": 42.05,
    "trust_ratio": 0.7482144249415813,
    "dealer_ratio": 0.0,
    "three_inst_ratio": 42.79821442494158,
    "three_inst_ratio_change_20": 0.8844202310579163
  },
  {
    "date": "2025-12-03",
    "code": "9904",
    "name": "寶成",
    "market": "TWSE",
    "foreign_ratio": 42.12,
    "trust_ratio": 0.7754028149435981,
    "dealer_ratio": 0.0,
    "three_inst_ratio": 42.895402814943594,
    "three_inst_ratio_change_20": 0.9201673470340239
  },
  {
    "date": "2025-12-04",
    "code": "9904",
    "name": "寶成",
    "market": "TWSE",
    "foreign_ratio": 42.13,
    "trust_ratio": 0.7695784378306925,
    "dealer_ratio": 0.0,
    "three_inst_ratio": 42.8995784378307,
    "three_inst_ratio_change_20": 0.7860942386816347
  },
  {
    "date": "2025-12-05",
    "code": "9904",
    "name": "寶成",
    "market": "TWSE",
    "foreign_ratio": 42.21,
    "trust_ratio": 0.7649293067568363,
    "dealer_ratio": 0.0,
    "three_inst_ratio": 42.974929306756835,
    "three_inst_ratio_change_20": 0.8715550539651389
  },
  {
    "date": "2025-12-08",
    "code": "9904",
    "name": "寶成",
    "market": "TWSE",
    "foreign_ratio": 42.18,
    "trust_ratio": 0.7595675351534111,
    "dealer_ratio": 0.0,
    "three_inst_ratio": 42.93956753515341,
    "three_inst_ratio_change_20": 0.9361932823617138
  },
  {
    "date": "2025-12-09",
    "code": "9904",
    "name": "寶成",
    "market": "TWSE",
    "foreign_ratio": 42.21,
    "trust_ratio": 0.7581886435992214,
    "dealer_ratio": 0.0,
    "three_inst_ratio": 42.96818864359922,
    "three_inst_ratio_change_20": 0.9673976543144462
  },
  {
    "date": "2025-12-10",
    "code": "9904",
    "name": "寶成",
    "market": "TWSE",
    "foreign_ratio": 42.19,
    "trust_ratio": 0.7559953057255241,
    "dealer_ratio": 0.0,
    "three_inst_ratio": 42.945995305725525,
    "three_inst_ratio_change_20": 0.767181215205035
  },
  {
    "date": "2025-12-11",
    "code": "9904",
    "name": "寶成",
    "market": "TWSE",
    "foreign_ratio": 42.27,
    "trust_ratio": 0.7540886190210301,
    "dealer_ratio": 0.0,
    "three_inst_ratio": 43.024088619021036,
    "three_inst_ratio_change_20": 0.7265456416584541
  },
  {
    "date": "2025-12-12",
    "code": "9904",
    "name": "寶成",
    "market": "TWSE",
    "foreign_ratio": 42.26,
    "trust_ratio": 0.753015178771919,
    "dealer_ratio": 0.0,
    "three_inst_ratio": 43.013015178771916,
    "three_inst_ratio_change_20": 0.4159056225923692
  },
  {
    "date": "2025-12-15",
    "code": "9904",
    "name": "寶成",
    "market": "TWSE",
    "foreign_ratio": 42.24,
    "trust_ratio": 0.7678448888396204,
    "dealer_ratio": 0.0,
    "three_inst_ratio": 43.00784488883962,
    "three_inst_ratio_change_20": 0.4625494100309808
  },
  {
    "date": "2025-12-16",
    "code": "9904",
    "name": "寶成",
    "market": "TWSE",
    "foreign_ratio": 42.32,
    "trust_ratio": 0.782036072992828,
    "dealer_ratio": 0.0,
    "three_inst_ratio": 43.10203607299283,
    "three_inst_ratio_change_20": 0.7836947646650501
  },
  {
    "date": "2025-12-17",
    "code": "9904",
    "name": "寶成",
    "market": "TWSE",
    "foreign_ratio": 42.34,
    "trust_ratio": 0.794949933834941,
    "dealer_ratio": 0.0,
    "three_inst_ratio": 43.134949933834946,
    "three_inst_ratio_change_20": 0.7703548616117928
  },
  {
    "date": "2025-12-18",
    "code": "9904",
    "name": "寶成",
    "market": "TWSE",
    "foreign_ratio": 42.27,
    "trust_ratio": 0.7976369958545764,
    "dealer_ratio": 0.0,
    "three_inst_ratio": 43.06763699585458,
    "three_inst_ratio_change_20": 0.6779684226320839
  },
  {
    "date": "2025-12-19",
    "code": "9904",
    "name": "寶成",
    "market": "TWSE",
    "foreign_ratio": 42.13,
    "trust_ratio": 0.847318221344542,
    "dealer_ratio": 0.0,
    "three_inst_ratio": 42.97731822134455,
    "three_inst_ratio_change_20": 0.6628999384897298
  },
  {
    "date": "2025-12-22",
    "code": "9904",
    "name": "寶成",
    "market": "TWSE",
    "foreign_ratio": 42.02,
    "trust_ratio": 0.8708599958214899,
    "dealer_ratio": 0.0,
    "three_inst_ratio": 42.890859995821494,
    "three_inst_ratio_change_20": 0.5850176591390053
  },
  {
    "date": "2025-12-23",
    "code": "9904",
    "name": "寶成",
    "market": "TWSE",
    "foreign_ratio": 41.96,
    "trust_ratio": 0.9068992454597027,
    "dealer_ratio": 0.0,
    "three_inst_ratio": 42.866899245459706,
    "three_inst_ratio_change_20": 0.5770705634353561
  },
  {
    "date": "2025-12-24",
    "code": "9904",
    "name": "寶成",
    "market": "TWSE",
    "foreign_ratio": 41.77,
    "trust_ratio": 0.9401524439151963,
    "dealer_ratio": 0.0,
    "three_inst_ratio": 42.7101524439152,
    "three_inst_ratio_change_20": 0.09079505482773698
  },
  {
    "date": "2025-12-25",
    "code": "9904",
    "name": "寶成",
    "market": "TWSE",
    "foreign_ratio": 0.0,
    "trust_ratio": 0.0,
    "dealer_ratio": 0.0,
    "three_inst_ratio": 0.0,
    "three_inst_ratio_change_20": -42.61162975662743
  },
  {
    "date": "2025-12-26",
    "code": "9904",
    "name": "寶成",
    "market": "TWSE",
    "foreign_ratio": 41.7,
    "trust_ratio": 0.9384279217041654,
    "dealer_ratio": 0.0,
    "three_inst_ratio": 42.63842792170417,
    "three_inst_ratio_change_20": -0.0032018349232529886
  },
  {
    "date": "2025-12-29",
    "code": "9904",
    "name": "寶成",
    "market": "TWSE",
    "foreign_ratio": 41.66,
    "trust_ratio": 0.9660851613041121,
    "dealer_ratio": 0.0,
    "three_inst_ratio": 42.62608516130411,
    "three_inst_ratio_change_20": -0.1368911031785487
  },
  {
    "date": "2025-12-30",
    "code": "9904",
    "name": "寶成",
    "market": "TWSE",
    "foreign_ratio": 41.57,
    "trust_ratio": 0.9803040366321828,
    "dealer_ratio": 0.0,
    "three_inst_ratio": 42.550304036632184,
    "three_inst_ratio_change_20": -0.24791038830939272
  },
  {
    "date": "2025-12-31",
    "code": "9904",
    "name": "寶成",
    "market": "TWSE",
    "foreign_ratio": 41.79,
    "trust_ratio": 0.7482159520284304,
    "dealer_ratio": 0.0,
    "three_inst_ratio": 42.53821595202843,
    "three_inst_ratio_change_20": -0.35718686291516377
  },
  {
    "date": "2026-01-01",
    "code": "9904",
    "name": "寶成",
    "market": "TWSE",
    "foreign_ratio": 0.0,
    "trust_ratio": 0.0,
    "dealer_ratio": 0.0,
    "three_inst_ratio": 0.0,
    "three_inst_ratio_change_20": -42.8995784378307
  },
  {
    "date": "2026-01-02",
    "code": "9904",
    "name": "寶成",
    "market": "TWSE",
    "foreign_ratio": 42.16,
    "trust_ratio": 0.42892523573604907,
    "dealer_ratio": 0.0,
    "three_inst_ratio": 42.58892523573605,
    "three_inst_ratio_change_20": -0.3860040710207855
  },
  {
    "date": "2026-01-05",
    "code": "9904",
    "name": "寶成",
    "market": "TWSE",
    "foreign_ratio": 42.47,
    "trust_ratio": 0.07718993044239193,
    "dealer_ratio": 0.0,
    "three_inst_ratio": 42.54718993044239,
    "three_inst_ratio_change_20": -0.39237760471101524
  },
  {
    "date": "2026-01-06",
    "code": "9904",
    "name": "寶成",
    "market": "TWSE",
    "foreign_ratio": 42.46,
    "trust_ratio": 0.07680106626009035,
    "dealer_ratio": 0.0,
    "three_inst_ratio": 42.53680106626009,
    "three_inst_ratio_change_20": -0.43138757733913025
  },
  {
    "date": "2026-01-07",
    "code": "9904",
    "name": "寶成",
    "market": "TWSE",
    "foreign_ratio": 42.79,
    "trust_ratio": 0.05060945674736101,
    "dealer_ratio": 0.0,
    "three_inst_ratio": 42.84060945674736,
    "three_inst_ratio_change_20": -0.10538584897816605
  },
  {
    "date": "2026-01-08",
    "code": "9904",
    "name": "寶成",
    "market": "TWSE",
    "foreign_ratio": 42.79,
    "trust_ratio": 0.01138049596932332,
    "dealer_ratio": 0.0,
    "three_inst_ratio": 42.80138049596932,
    "three_inst_ratio_change_20": -0.22270812305171717
  },
  {
    "date": "2026-01-09",
    "code": "9904",
    "name": "寶成",
    "market": "TWSE",
    "foreign_ratio": 42.92,
    "trust_ratio": 0.009884968915127433,
    "dealer_ratio": 0.0,
    "three_inst_ratio": 42.92988496891513,
    "three_inst_ratio_change_20": -0.08313020985678321
  },
  {
    "date": "2026-01-12",
    "code": "9904",
    "name": "寶成",
    "market": "TWSE",
    "foreign_ratio": 43.33,
    "trust_ratio": -0.06557480606252379,
    "dealer_ratio": 0.0,
    "three_inst_ratio": 43.26442519393748,
    "three_inst_ratio_change_20": 0.2565803050978559
  },
  {
    "date": "2026-01-13",
    "code": "9904",
    "name": "寶成",
    "market": "TWSE",
    "foreign_ratio": 43.14,
    "trust_ratio": -0.07607281550939729,
    "dealer_ratio": 0.0,
    "three_inst_ratio": 43.0639271844906,
    "three_inst_ratio_change_20": -0.03810888850222938
  },
  {
    "date": "2026-01-14",
    "code": "9904",
    "name": "寶成",
    "market": "TWSE",
    "foreign_ratio": 43.3,
    "trust_ratio": -0.10642292005900596,
    "dealer_ratio": 0.0,
    "three_inst_ratio": 43.193577079940994,
    "three_inst_ratio_change_20": 0.05862714610604769
  },
  {
    "date": "2026-01-15",
    "code": "9904",
    "name": "寶成",
    "market": "TWSE",
    "foreign_ratio": 43.37,
    "trust_ratio": -0.14623485472549455,
    "dealer_ratio": 0.0,
    "three_inst_ratio": 43.223765145274506,
    "three_inst_ratio_change_20": 0.1561281494199278
  },
  {
    "date": "2026-01-16",
    "code": "9904",
    "name": "寶成",
    "market": "TWSE",
    "foreign_ratio": 43.37,
    "trust_ratio": -0.1548263471441906,
    "dealer_ratio": 0.0,
    "three_inst_ratio": 43.21517365285581,
    "three_inst_ratio_change_20": 0.23785543151126376
  },
  {
    "date": "2026-01-19",
    "code": "9904",
    "name": "寶成",
    "market": "TWSE",
    "foreign_ratio": 43.34,
    "trust_ratio": -0.11070412500802446,
    "dealer_ratio": 0.0,
    "three_inst_ratio": 43.229295874991976,
    "three_inst_ratio_change_20": 0.3384358791704827
  },
  {
    "date": "2026-01-20",
    "code": "9904",
    "name": "寶成",
    "market": "TWSE",
    "foreign_ratio": 43.41,
    "trust_ratio": -0.14574852846695857,
    "dealer_ratio": 0.0,
    "three_inst_ratio": 43.264251471533036,
    "three_inst_ratio_change_20": 0.39735222607333043
  },
  {
    "date": "2026-01-21",
    "code": "9904",
    "name": "寶成",
    "market": "TWSE",
    "foreign_ratio": 43.24,
    "trust_ratio": -0.15820246468539295,
    "dealer_ratio": 0.0,
    "three_inst_ratio": 43.08179753531461,
    "three_inst_ratio_change_20": 0.37164509139940805
  },
  {
    "date": "2026-01-22",
    "code": "9904",
    "name": "寶成",
    "market": "TWSE",
    "foreign_ratio": 43.27,
    "trust_ratio": -0.201888788364306,
    "dealer_ratio": 0.0,
    "three_inst_ratio": 43.068111211635696,
    "three_inst_ratio_change_20": 43.068111211635696
  },
  {
    "date": "2026-01-23",
    "code": "9904",
    "name": "寶成",
    "market": "TWSE",
    "foreign_ratio": 43.25,
    "trust_ratio": -0.22489078854300024,
    "dealer_ratio": 0.0,
    "three_inst_ratio": 43.025109211457,
    "three_inst_ratio_change_20": 0.3866812897528291
  },
  {
    "date": "2026-01-26",
    "code": "9904",
    "name": "寶成",
    "market": "TWSE",
    "foreign_ratio": 43.4,
    "trust_ratio": -0.21391323989025332,
    "dealer_ratio": 0.0,
    "three_inst_ratio": 43.186086760109745,
    "three_inst_ratio_change_20": 0.5600015988056342
  },
  {
    "date": "2026-01-27",
    "code": "9904",
    "name": "寶成",
    "market": "TWSE",
    "foreign_ratio": 43.47,
    "trust_ratio": -0.24402572972614567,
    "dealer_ratio": 0.0,
    "three_inst_ratio": 43.22597427027385,
    "three_inst_ratio_change_20": 0.675670233641668
  },
  {
    "date": "2026-01-28",
    "code": "9904",
    "name": "寶成",
    "market": "TWSE",
    "foreign_ratio": 43.34,
    "trust_ratio": -0.2554677163925918,
    "dealer_ratio": 0.0,
    "three_inst_ratio": 43.08453228360741,
    "three_inst_ratio_change_20": 0.5463163315789785
  },
  {
    "date": "2026-01-29",
    "code": "9904",
    "name": "寶成",
    "market": "TWSE",
    "foreign_ratio": 43.37,
    "trust_ratio": -0.27544340372431225,
    "dealer_ratio": 0.0,
    "three_inst_ratio": 43.09455659627569,
    "three_inst_ratio_change_20": 43.09455659627569
  },
  {
    "date": "2026-01-30",
    "code": "9904",
    "name": "寶成",
    "market": "TWSE",
    "foreign_ratio": 43.28,
    "trust_ratio": -0.300028212454443,
    "dealer_ratio": 0.0,
    "three_inst_ratio": 42.97997178754556,
    "three_inst_ratio_change_20": 0.3910465518095094
  },
  {
    "date": "2026-02-02",
    "code": "9904",
    "name": "寶成",
    "market": "TWSE",
    "foreign_ratio": 43.3,
    "trust_ratio": -0.33174353264712636,
    "dealer_ratio": 0.0,
    "three_inst_ratio": 42.96825646735287,
    "three_inst_ratio_change_20": 0.42106653691048024
  },
  {
    "date": "2026-02-03",
    "code": "9904",
    "name": "寶成",
    "market": "TWSE",
    "foreign_ratio": 43.25,
    "trust_ratio": -0.35253577028467986,
    "dealer_ratio": 0.0,
    "three_inst_ratio": 42.89746422971532,
    "three_inst_ratio_change_20": 0.36066316345522864
  },
  {
    "date": "2026-02-04",
    "code": "9904",
    "name": "寶成",
    "market": "TWSE",
    "foreign_ratio": 43.31,
    "trust_ratio": -0.3654651056068635,
    "dealer_ratio": 0.0,
    "three_inst_ratio": 42.944534894393136,
    "three_inst_ratio_change_20": 0.10392543764577766
  },
  {
    "date": "2026-02-05",
    "code": "9904",
    "name": "寶成",
    "market": "TWSE",
    "foreign_ratio": 43.39,
    "trust_ratio": -0.3649618795871977,
    "dealer_ratio": 0.0,
    "three_inst_ratio": 43.0250381204128,
    "three_inst_ratio_change_20": 0.22365762444348292
  },
  {
    "date": "2026-02-06",
    "code": "9904",
    "name": "寶成",
    "market": "TWSE",
    "foreign_ratio": 43.42,
    "trust_ratio": -0.3653012322203259,
    "dealer_ratio": 0.0,
    "three_inst_ratio": 43.054698767779676,
    "three_inst_ratio_change_20": 0.12481379886454391
  },
  {
    "date": "2026-02-09",
    "code": "9904",
    "name": "寶成",
    "market": "TWSE",
    "foreign_ratio": 43.51,
    "trust_ratio": -0.3901757802286215,
    "dealer_ratio": 0.0,
    "three_inst_ratio": 43.119824219771374,
    "three_inst_ratio_change_20": -0.14460097416610296
  },
  {
    "date": "2026-02-10",
    "code": "9904",
    "name": "寶成",
    "market": "TWSE",
    "foreign_ratio": 43.51,
    "trust_ratio": -0.3999949826034487,
    "dealer_ratio": 0.0,
    "three_inst_ratio": 43.11000501739655,
    "three_inst_ratio_change_20": 0.0460778329059508
  },
  {
    "date": "2026-02-11",
    "code": "9904",
    "name": "寶成",
    "market": "TWSE",
    "foreign_ratio": 43.57,
    "trust_ratio": -0.4093271800144736,
    "dealer_ratio": 0.0,
    "three_inst_ratio": 43.16067281998553,
    "three_inst_ratio_change_20": -0.03290425995546542
  },
  {
    "date": "2026-02-17",
    "code": "9904",
    "name": "寶成",
    "market": "TWSE",
    "foreign_ratio": 0.0,
    "trust_ratio": 0.0,
    "dealer_ratio": 0.0,
    "three_inst_ratio": 0.0,
    "three_inst_ratio_change_20": -43.223765145274506
  },
  {
    "date": "2026-02-18",
    "code": "9904",
    "name": "寶成",
    "market": "TWSE",
    "foreign_ratio": 0.0,
    "trust_ratio": 0.0,
    "dealer_ratio": 0.0,
    "three_inst_ratio": 0.0,
    "three_inst_ratio_change_20": -43.21517365285581
  },
  {
    "date": "2026-02-19",
    "code": "9904",
    "name": "寶成",
    "market": "TWSE",
    "foreign_ratio": 0.0,
    "trust_ratio": 0.0,
    "dealer_ratio": 0.0,
    "three_inst_ratio": 0.0,
    "three_inst_ratio_change_20": -43.229295874991976
  },
  {
    "date": "2026-02-20",
    "code": "9904",
    "name": "寶成",
    "market": "TWSE",
    "foreign_ratio": 0.0,
    "trust_ratio": 0.0,
    "dealer_ratio": 0.0,
    "three_inst_ratio": 0.0,
    "three_inst_ratio_change_20": -43.264251471533036
  },
  {
    "date": "2026-02-23",
    "code": "9904",
    "name": "寶成",
    "market": "TWSE",
    "foreign_ratio": 43.68,
    "trust_ratio": -0.47374204484170196,
    "dealer_ratio": 0.0,
    "three_inst_ratio": 43.2062579551583,
    "three_inst_ratio_change_20": 0.12446041984369316
  },
  {
    "date": "2026-02-24",
    "code": "9904",
    "name": "寶成",
    "market": "TWSE",
    "foreign_ratio": 43.73,
    "trust_ratio": -0.4868068497350304,
    "dealer_ratio": 0.0,
    "three_inst_ratio": 43.243193150264965,
    "three_inst_ratio_change_20": 0.17508193862926902
  },
  {
    "date": "2026-02-25",
    "code": "9904",
    "name": "寶成",
    "market": "TWSE",
    "foreign_ratio": 43.75,
    "trust_ratio": -0.5197575492533536,
    "dealer_ratio": 0.0,
    "three_inst_ratio": 43.230242450746644,
    "three_inst_ratio_change_20": 0.2051332392896441
  },
  {
    "date": "2026-02-26",
    "code": "9904",
    "name": "寶成",
    "market": "TWSE",
    "foreign_ratio": 43.84,
    "trust_ratio": -0.6069643889146331,
    "dealer_ratio": 0.0,
    "three_inst_ratio": 43.23303561108537,
    "three_inst_ratio_change_20": 0.04694885097562462
  },
  {
    "date": "2026-03-02",
    "code": "9904",
    "name": "寶成",
    "market": "TWSE",
    "foreign_ratio": 43.87,
    "trust_ratio": -0.6492783705451758,
    "dealer_ratio": 0.0,
    "three_inst_ratio": 43.22072162945482,
    "three_inst_ratio_change_20": -0.005252640819030319
  },
  {
    "date": "2026-03-03",
    "code": "9904",
    "name": "寶成",
    "market": "TWSE",
    "foreign_ratio": 43.81,
    "trust_ratio": -0.686166001766209,
    "dealer_ratio": 0.0,
    "three_inst_ratio": 43.12383399823379,
    "three_inst_ratio_change_20": 0.03930171462638299
  },
  {
    "date": "2026-03-04",
    "code": "9904",
    "name": "寶成",
    "market": "TWSE",
    "foreign_ratio": 43.67,
    "trust_ratio": -0.6867005160986491,
    "dealer_ratio": 0.0,
    "three_inst_ratio": 42.983299483901355,
    "three_inst_ratio_change_20": -0.11125711237433222
  },
  {
    "date": "2026-03-05",
    "code": "9904",
    "name": "寶成",
    "market": "TWSE",
    "foreign_ratio": 43.76,
    "trust_ratio": -0.6907727476961874,
    "dealer_ratio": 0.0,
    "three_inst_ratio": 43.06922725230381,
    "three_inst_ratio_change_20": 0.08925546475825286
  },
  {
    "date": "2026-03-06",
    "code": "9904",
    "name": "寶成",
    "market": "TWSE",
    "foreign_ratio": 43.82,
    "trust_ratio": -0.6901619129565566,
    "dealer_ratio": 0.0,
    "three_inst_ratio": 43.129838087043446,
    "three_inst_ratio_change_20": 0.1615816196905726
  },
  {
    "date": "2026-03-09",
    "code": "9904",
    "name": "寶成",
    "market": "TWSE",
    "foreign_ratio": 43.82,
    "trust_ratio": -0.6893050814931713,
    "dealer_ratio": 0.0,
    "three_inst_ratio": 43.130694918506826,
    "three_inst_ratio_change_20": 0.2332306887915081
  },
  {
    "date": "2026-03-10",
    "code": "9904",
    "name": "寶成",
    "market": "TWSE",
    "foreign_ratio": 43.79,
    "trust_ratio": -0.7325046716903885,
    "dealer_ratio": 0.0,
    "three_inst_ratio": 43.057495328309614,
    "three_inst_ratio_change_20": 0.11296043391647714
  },
  {
    "date": "2026-03-11",
    "code": "9904",
    "name": "寶成",
    "market": "TWSE",
    "foreign_ratio": 43.82,
    "trust_ratio": -0.7330219808443291,
    "dealer_ratio": 0.0,
    "three_inst_ratio": 43.08697801915567,
    "three_inst_ratio_change_20": 0.06193989874287098
  },
  {
    "date": "2026-03-12",
    "code": "9904",
    "name": "寶成",
    "market": "TWSE",
    "foreign_ratio": 43.86,
    "trust_ratio": -0.7668212655570527,
    "dealer_ratio": 0.0,
    "three_inst_ratio": 43.093178734442944,
    "three_inst_ratio_change_20": 0.03847996666326736
  },
  {
    "date": "2026-03-13",
    "code": "9904",
    "name": "寶成",
    "market": "TWSE",
    "foreign_ratio": 43.62,
    "trust_ratio": -0.7638943490963221,
    "dealer_ratio": 0.0,
    "three_inst_ratio": 42.85610565090367,
    "three_inst_ratio_change_20": -0.2637185688677022
  },
  {
    "date": "2026-03-16",
    "code": "9904",
    "name": "寶成",
    "market": "TWSE",
    "foreign_ratio": 43.41,
    "trust_ratio": -0.7613050206350275,
    "dealer_ratio": 0.0,
    "three_inst_ratio": 42.64869497936497,
    "three_inst_ratio_change_20": -0.4613100380315842
  },
  {
    "date": "2026-03-17",
    "code": "9904",
    "name": "寶成",
    "market": "TWSE",
    "foreign_ratio": 43.33,
    "trust_ratio": -0.7663018184815233,
    "dealer_ratio": 0.0,
    "three_inst_ratio": 42.563698181518475,
    "three_inst_ratio_change_20": -0.5969746384670529
  },
  {
    "date": "2026-03-18",
    "code": "9904",
    "name": "寶成",
    "market": "TWSE",
    "foreign_ratio": 43.27,
    "trust_ratio": -0.7907517684752489,
    "dealer_ratio": 0.0,
    "three_inst_ratio": 42.47924823152476,
    "three_inst_ratio_change_20": 42.47924823152476
  },
  {
    "date": "2026-03-19",
    "code": "9904",
    "name": "寶成",
    "market": "TWSE",
    "foreign_ratio": 43.11,
    "trust_ratio": -0.7912097587889186,
    "dealer_ratio": 0.0,
    "three_inst_ratio": 42.31879024121108,
    "three_inst_ratio_change_20": 42.31879024121108
  },
  {
    "date": "2026-03-20",
    "code": "9904",
    "name": "寶成",
    "market": "TWSE",
    "foreign_ratio": 43.1,
    "trust_ratio": -0.7702728890591259,
    "dealer_ratio": 0.0,
    "three_inst_ratio": 42.32972711094087,
    "three_inst_ratio_change_20": 42.32972711094087
  },
  {
    "date": "2026-03-23",
    "code": "9904",
    "name": "寶成",
    "market": "TWSE",
    "foreign_ratio": 43.05,
    "trust_ratio": -0.7701793295381726,
    "dealer_ratio": 0.0,
    "three_inst_ratio": 42.279820670461824,
    "three_inst_ratio_change_20": 42.279820670461824
  },
  {
    "date": "2026-03-24",
    "code": "9904",
    "name": "寶成",
    "market": "TWSE",
    "foreign_ratio": 42.99,
    "trust_ratio": -0.7689915953222239,
    "dealer_ratio": 0.0,
    "three_inst_ratio": 42.221008404677775,
    "three_inst_ratio_change_20": -0.9852495504805248
  },
  {
    "date": "2026-03-25",
    "code": "9904",
    "name": "寶成",
    "market": "TWSE",
    "foreign_ratio": 43.0,
    "trust_ratio": -0.7874523785643968,
    "dealer_ratio": 0.0,
    "three_inst_ratio": 42.212547621435604,
    "three_inst_ratio_change_20": -1.0306455288293606
  },
  {
    "date": "2026-03-26",
    "code": "9904",
    "name": "寶成",
    "market": "TWSE",
    "foreign_ratio": 42.96,
    "trust_ratio": -0.7877917311975251,
    "dealer_ratio": 0.0,
    "three_inst_ratio": 42.17220826880248,
    "three_inst_ratio_change_20": -1.0580341819441657
  },
  {
    "date": "2026-03-27",
    "code": "9904",
    "name": "寶成",
    "market": "TWSE",
    "foreign_ratio": 42.97,
    "trust_ratio": -0.7877577959342121,
    "dealer_ratio": 0.0,
    "three_inst_ratio": 42.18224220406579,
    "three_inst_ratio_change_20": -1.050793407019583
  },
  {
    "date": "2026-03-30",
    "code": "9904",
    "name": "寶成",
    "market": "TWSE",
    "foreign_ratio": 42.88,
    "trust_ratio": -0.7873845080377713,
    "dealer_ratio": 0.0,
    "three_inst_ratio": 42.092615491962235,
    "three_inst_ratio_change_20": -1.128106137492587
  },
  {
    "date": "2026-03-31",
    "code": "9904",
    "name": "寶成",
    "market": "TWSE",
    "foreign_ratio": 42.88,
    "trust_ratio": -0.7867736732981405,
    "dealer_ratio": 0.0,
    "three_inst_ratio": 42.09322632670186,
    "three_inst_ratio_change_20": -1.0306076715319321
  },
  {
    "date": "2026-04-01",
    "code": "9904",
    "name": "寶成",
    "market": "TWSE",
    "foreign_ratio": 42.97,
    "trust_ratio": -0.7815815780112794,
    "dealer_ratio": 0.0,
    "three_inst_ratio": 42.18841842198872,
    "three_inst_ratio_change_20": -0.7948810619126334
  },
  {
    "date": "2026-04-02",
    "code": "9904",
    "name": "寶成",
    "market": "TWSE",
    "foreign_ratio": 42.93,
    "trust_ratio": -0.7798764328356002,
    "dealer_ratio": 0.0,
    "three_inst_ratio": 42.1501235671644,
    "three_inst_ratio_change_20": -0.9191036851394117
  },
  {
    "date": "2026-04-03",
    "code": "9904",
    "name": "寶成",
    "market": "TWSE",
    "foreign_ratio": 0.0,
    "trust_ratio": 0.0,
    "dealer_ratio": 0.0,
    "three_inst_ratio": 0.0,
    "three_inst_ratio_change_20": -43.129838087043446
  },
  {
    "date": "2026-04-07",
    "code": "9904",
    "name": "寶成",
    "market": "TWSE",
    "foreign_ratio": 42.92,
    "trust_ratio": -0.7815904690502673,
    "dealer_ratio": 0.0,
    "three_inst_ratio": 42.13840953094974,
    "three_inst_ratio_change_20": -0.9922853875570894
  },
  {
    "date": "2026-04-08",
    "code": "9904",
    "name": "寶成",
    "market": "TWSE",
    "foreign_ratio": 42.97,
    "trust_ratio": -0.7807420874674469,
    "dealer_ratio": 0.0,
    "three_inst_ratio": 42.189257912532554,
    "three_inst_ratio_change_20": -0.8682374157770596
  },
  {
    "date": "2026-04-09",
    "code": "9904",
    "name": "寶成",
    "market": "TWSE",
    "foreign_ratio": 42.84,
    "trust_ratio": -0.7798770097350766,
    "dealer_ratio": 0.0,
    "three_inst_ratio": 42.06012299026493,
    "three_inst_ratio_change_20": -1.0268550288907434
  },
  {
    "date": "2026-04-10",
    "code": "9904",
    "name": "寶成",
    "market": "TWSE",
    "foreign_ratio": 42.67,
    "trust_ratio": -0.7878780625073929,
    "dealer_ratio": 0.0,
    "three_inst_ratio": 41.882121937492606,
    "three_inst_ratio_change_20": -1.2110567969503379
  },
  {
    "date": "2026-04-13",
    "code": "9904",
    "name": "寶成",
    "market": "TWSE",
    "foreign_ratio": 42.47,
    "trust_ratio": -0.7789285869960099,
    "dealer_ratio": 0.0,
    "three_inst_ratio": 41.69107141300399,
    "three_inst_ratio_change_20": -1.1650342378996825
  },
  {
    "date": "2026-04-14",
    "code": "9904",
    "name": "寶成",
    "market": "TWSE",
    "foreign_ratio": 42.37,
    "trust_ratio": -0.8288906267898889,
    "dealer_ratio": 0.0,
    "three_inst_ratio": 41.541109373210105,
    "three_inst_ratio_change_20": -1.1075856061548635
  },
  {
    "date": "2026-04-15",
    "code": "9904",
    "name": "寶成",
    "market": "TWSE",
    "foreign_ratio": 42.31,
    "trust_ratio": -0.8826629518837945,
    "dealer_ratio": 0.0,
    "three_inst_ratio": 41.42733704811621,
    "three_inst_ratio_change_20": -1.1363611334022679
  },
  {
    "date": "2026-04-16",
    "code": "9904",
    "name": "寶成",
    "market": "TWSE",
    "foreign_ratio": 42.27,
    "trust_ratio": -0.9522572880799317,
    "dealer_ratio": 0.0,
    "three_inst_ratio": 41.31774271192007,
    "three_inst_ratio_change_20": -1.1615055196046882
  },
  {
    "date": "2026-04-17",
    "code": "9904",
    "name": "寶成",
    "market": "TWSE",
    "foreign_ratio": 42.1,
    "trust_ratio": -1.0105675383898172,
    "dealer_ratio": 0.0,
    "three_inst_ratio": 41.08943246161019,
    "three_inst_ratio_change_20": -1.229357779600896
  },
  {
    "date": "2026-04-20",
    "code": "9904",
    "name": "寶成",
    "market": "TWSE",
    "foreign_ratio": 41.84,
    "trust_ratio": -1.0190699507423173,
    "dealer_ratio": 0.0,
    "three_inst_ratio": 40.82093004925768,
    "three_inst_ratio_change_20": -1.5087970616831896
  },
  {
    "date": "2026-04-21",
    "code": "9904",
    "name": "寶成",
    "market": "TWSE",
    "foreign_ratio": 41.29,
    "trust_ratio": -0.8914085782684574,
    "dealer_ratio": 0.0,
    "three_inst_ratio": 40.39859142173154,
    "three_inst_ratio_change_20": -1.8812292487302855
  },
  {
    "date": "2026-04-22",
    "code": "9904",
    "name": "寶成",
    "market": "TWSE",
    "foreign_ratio": 40.77,
    "trust_ratio": -0.8066791146348035,
    "dealer_ratio": 0.0,
    "three_inst_ratio": 39.9633208853652,
    "three_inst_ratio_change_20": -2.257687519312576
  },
  {
    "date": "2026-04-23",
    "code": "9904",
    "name": "寶成",
    "market": "TWSE",
    "foreign_ratio": 40.39,
    "trust_ratio": -0.7165995191930405,
    "dealer_ratio": 0.0,
    "three_inst_ratio": 39.67340048080696,
    "three_inst_ratio_change_20": -2.5391471406286428
  },
  {
    "date": "2026-04-24",
    "code": "9904",
    "name": "寶成",
    "market": "TWSE",
    "foreign_ratio": 40.11,
    "trust_ratio": -0.608616119985858,
    "dealer_ratio": 0.0,
    "three_inst_ratio": 39.50138388001414,
    "three_inst_ratio_change_20": -2.67082438878834
  },
  {
    "date": "2026-04-27",
    "code": "9904",
    "name": "寶成",
    "market": "TWSE",
    "foreign_ratio": 39.98,
    "trust_ratio": -0.639167494582175,
    "dealer_ratio": 0.0,
    "three_inst_ratio": 39.34083250541782,
    "three_inst_ratio_change_20": -2.841409698647965
  },
  {
    "date": "2026-04-28",
    "code": "9904",
    "name": "寶成",
    "market": "TWSE",
    "foreign_ratio": 39.79,
    "trust_ratio": -0.6726196215512084,
    "dealer_ratio": 0.0,
    "three_inst_ratio": 39.11738037844879,
    "three_inst_ratio_change_20": -2.975235113513442
  },
  {
    "date": "2026-04-29",
    "code": "9904",
    "name": "寶成",
    "market": "TWSE",
    "foreign_ratio": 39.67,
    "trust_ratio": -0.7232849696772456,
    "dealer_ratio": 0.0,
    "three_inst_ratio": 38.94671503032276,
    "three_inst_ratio_change_20": -3.146511296379103
  },
  {
    "date": "2026-04-30",
    "code": "9904",
    "name": "寶成",
    "market": "TWSE",
    "foreign_ratio": 39.54,
    "trust_ratio": -0.7907985991386207,
    "dealer_ratio": 0.0,
    "three_inst_ratio": 38.74920140086138,
    "three_inst_ratio_change_20": -3.439217021127341
  },
  {
    "date": "2026-05-04",
    "code": "9904",
    "name": "寶成",
    "market": "TWSE",
    "foreign_ratio": 39.4,
    "trust_ratio": -0.8061179271853994,
    "dealer_ratio": 0.0,
    "three_inst_ratio": 38.5938820728146,
    "three_inst_ratio_change_20": -3.5562414943497984
  },
  {
    "date": "2026-05-05",
    "code": "9904",
    "name": "寶成",
    "market": "TWSE",
    "foreign_ratio": 39.39,
    "trust_ratio": -0.8228327411301278,
    "dealer_ratio": 0.0,
    "three_inst_ratio": 38.56716725886987,
    "three_inst_ratio_change_20": 38.56716725886987
  },
  {
    "date": "2026-05-06",
    "code": "9904",
    "name": "寶成",
    "market": "TWSE",
    "foreign_ratio": 39.21,
    "trust_ratio": -0.8571059317950149,
    "dealer_ratio": 0.0,
    "three_inst_ratio": 38.35289406820499,
    "three_inst_ratio_change_20": -3.7855154627447476
  },
  {
    "date": "2026-05-07",
    "code": "9904",
    "name": "寶成",
    "market": "TWSE",
    "foreign_ratio": 39.21,
    "trust_ratio": -0.8859269133797479,
    "dealer_ratio": 0.0,
    "three_inst_ratio": 38.32407308662025,
    "three_inst_ratio_change_20": -3.8651848259123014
  },
  {
    "date": "2026-05-08",
    "code": "9904",
    "name": "寶成",
    "market": "TWSE",
    "foreign_ratio": 39.06,
    "trust_ratio": -0.9355546908299959,
    "dealer_ratio": 0.0,
    "three_inst_ratio": 38.12444530917001,
    "three_inst_ratio_change_20": -3.9356776810949228
  },
  {
    "date": "2026-05-11",
    "code": "9904",
    "name": "寶成",
    "market": "TWSE",
    "foreign_ratio": 38.83,
    "trust_ratio": -0.968196443711119,
    "dealer_ratio": 0.0,
    "three_inst_ratio": 37.861803556288876,
    "three_inst_ratio_change_20": -4.0203183812037295
  },
  {
    "date": "2026-05-12",
    "code": "9904",
    "name": "寶成",
    "market": "TWSE",
    "foreign_ratio": 38.7,
    "trust_ratio": -1.0549767849830833,
    "dealer_ratio": 0.0,
    "three_inst_ratio": 37.64502321501692,
    "three_inst_ratio_change_20": -4.046048197987069
  },
  {
    "date": "2026-05-13",
    "code": "9904",
    "name": "寶成",
    "market": "TWSE",
    "foreign_ratio": 38.67,
    "trust_ratio": -1.07326582185763,
    "dealer_ratio": 0.0,
    "three_inst_ratio": 37.59673417814237,
    "three_inst_ratio_change_20": -3.9443751950677353
  },
  {
    "date": "2026-05-14",
    "code": "9904",
    "name": "寶成",
    "market": "TWSE",
    "foreign_ratio": 38.62,
    "trust_ratio": -1.103276064745161,
    "dealer_ratio": 0.0,
    "three_inst_ratio": 37.51672393525484,
    "three_inst_ratio_change_20": -3.9106131128613697
  },
  {
    "date": "2026-05-15",
    "code": "9904",
    "name": "寶成",
    "market": "TWSE",
    "foreign_ratio": 38.56,
    "trust_ratio": -1.1271325548540718,
    "dealer_ratio": 0.0,
    "three_inst_ratio": 37.43286744514593,
    "three_inst_ratio_change_20": -3.884875266774138
  },
  {
    "date": "2026-05-18",
    "code": "9904",
    "name": "寶成",
    "market": "TWSE",
    "foreign_ratio": 38.51,
    "trust_ratio": -1.1392354647087983,
    "dealer_ratio": 0.0,
    "three_inst_ratio": 37.3707645352912,
    "three_inst_ratio_change_20": -3.718667926318986
  },
  {
    "date": "2026-05-19",
    "code": "9904",
    "name": "寶成",
    "market": "TWSE",
    "foreign_ratio": 38.45,
    "trust_ratio": -1.1944591670793299,
    "dealer_ratio": 0.0,
    "three_inst_ratio": 37.25554083292067,
    "three_inst_ratio_change_20": -3.5653892163370102
  },
  {
    "date": "2026-05-20",
    "code": "9904",
    "name": "寶成",
    "market": "TWSE",
    "foreign_ratio": 38.01,
    "trust_ratio": -1.2022157162794775,
    "dealer_ratio": 0.0,
    "three_inst_ratio": 36.80778428372052,
    "three_inst_ratio_change_20": -3.590807138011016
  },
  {
    "date": "2026-05-21",
    "code": "9904",
    "name": "寶成",
    "market": "TWSE",
    "foreign_ratio": 37.97,
    "trust_ratio": -1.211770800499941,
    "dealer_ratio": 0.0,
    "three_inst_ratio": 36.75822919950006,
    "three_inst_ratio_change_20": -3.205091685865142
  },
  {
    "date": "2026-05-22",
    "code": "9904",
    "name": "寶成",
    "market": "TWSE",
    "foreign_ratio": 37.77,
    "trust_ratio": -1.229527223416793,
    "dealer_ratio": 0.0,
    "three_inst_ratio": 36.54047277658321,
    "three_inst_ratio_change_20": -3.1329277042237536
  },
  {
    "date": "2026-05-25",
    "code": "9904",
    "name": "寶成",
    "market": "TWSE",
    "foreign_ratio": 33.02,
    "trust_ratio": -1.2566655928406867,
    "dealer_ratio": 0.0,
    "three_inst_ratio": 31.763334407159316,
    "three_inst_ratio_change_20": -7.738049472854822
  },
  {
    "date": "2026-05-26",
    "code": "9904",
    "name": "寶成",
    "market": "TWSE",
    "foreign_ratio": 32.87,
    "trust_ratio": -1.2827702602088087,
    "dealer_ratio": 0.0,
    "three_inst_ratio": 31.587229739791187,
    "three_inst_ratio_change_20": -7.753602765626635
  },
  {
    "date": "2026-05-27",
    "code": "9904",
    "name": "寶成",
    "market": "TWSE",
    "foreign_ratio": 32.58,
    "trust_ratio": -1.3030319539397297,
    "dealer_ratio": 0.0,
    "three_inst_ratio": 31.27696804606027,
    "three_inst_ratio_change_20": -7.840412332388524
  },
  {
    "date": "2026-05-28",
    "code": "9904",
    "name": "寶成",
    "market": "TWSE",
    "foreign_ratio": 32.43,
    "trust_ratio": -1.3794834191171712,
    "dealer_ratio": 0.0,
    "three_inst_ratio": 31.050516580882828,
    "three_inst_ratio_change_20": -7.896198449439929
  },
  {
    "date": "2026-05-29",
    "code": "9904",
    "name": "寶成",
    "market": "TWSE",
    "foreign_ratio": 32.37,
    "trust_ratio": -1.4442415391328087,
    "dealer_ratio": 0.0,
    "three_inst_ratio": 30.92575846086719,
    "three_inst_ratio_change_20": -7.823442939994191
  },
  {
    "date": "2026-06-01",
    "code": "9904",
    "name": "寶成",
    "market": "TWSE",
    "foreign_ratio": 32.37,
    "trust_ratio": -1.563944583330863,
    "dealer_ratio": 0.0,
    "three_inst_ratio": 30.806055416669135,
    "three_inst_ratio_change_20": -7.787826656145466
  }
]